{"31352832": {"addr:housenumber": null, "amenity": null, "name": "Greene King Brewery", "point": {"lat": "52.2391076762699)", "lng": "0.717130790868816"}, "industry": null, "addr:interpolation": null, "addr:housename": null, "microbrewery": null, "craft": null, "osm_id": 31352832, "type": "way"}, "99572214": {"addr:housenumber": null, "amenity": null, "name": "Former Brewery", "point": {"lat": "51.8304074272023)", "lng": "0.448217856385418"}, "industry": null, "addr:interpolation": null, "addr:housename": null, "microbrewery": null, "craft": null, "osm_id": 99572214, "type": "way"}, "34654327": {"addr:housenumber": null, "amenity": null, "name": "The Old Brewery", "point": {"lat": "53.8831635112801)", "lng": "-1.26037098809901"}, "industry": null, "addr:interpolation": null, "addr:housename": null, "microbrewery": null, "craft": null, "osm_id": 34654327, "type": "way"}, "41699276": {"addr:housenumber": null, "amenity": null, "name": "Magor Brewery", "point": {"lat": "51.5842025744626)", "lng": "-2.84507994624135"}, "industry": null, "addr:interpolation": null, "addr:housename": null, "microbrewery": null, "craft": null, "osm_id": 41699276, "type": "way"}, "306202575": {"addr:housenumber": null, "amenity": null, "name": "Saint Francis Abbey Brewery", "point": {"lat": "52.6556430947512)", "lng": "-7.25439559899018"}, "industry": null, "addr:interpolation": null, "addr:housename": null, "microbrewery": null, "craft": null, "osm_id": 306202575, "type": "node"}, "29149010": {"addr:housenumber": null, "amenity": null, "name": "Coors Brewery", "point": {"lat": "52.8098187850487)", "lng": "-1.62978828188117"}, "industry": null, "addr:interpolation": null, "addr:housename": null, "microbrewery": null, "craft": null, "osm_id": 29149010, "type": "way"}, "34929891": {"addr:housenumber": null, "amenity": null, "name": "Bulmers Brewery", "point": {"lat": "52.3610093492964)", "lng": "-7.64840415405657"}, "industry": null, "addr:interpolation": null, "addr:housename": null, "microbrewery": null, "craft": null, "osm_id": 34929891, "type": "way"}, "112236183": {"addr:housenumber": null, "amenity": null, "name": "Freedom Brewery", "point": {"lat": "52.8408060732909)", "lng": "-1.86308887243476"}, "industry": null, "addr:interpolation": null, "addr:housename": null, "microbrewery": null, "craft": null, "osm_id": 112236183, "type": "way"}, "35065752": {"addr:housenumber": null, "amenity": null, "name": "The Brewery", "point": {"lat": "51.9033161784423)", "lng": "-2.07594511573661"}, "industry": null, "addr:interpolation": null, "addr:housename": null, "microbrewery": null, "craft": null, "osm_id": 35065752, "type": "way"}, "58706528": {"addr:housenumber": null, "amenity": "shop", "name": "Arran Brewery", "point": {"lat": "55.5922055947162)", "lng": "-5.15683189928216"}, "industry": null, "addr:interpolation": null, "addr:housename": null, "microbrewery": null, "craft": null, "osm_id": 58706528, "type": "node"}, "129111331": {"addr:housenumber": null, "amenity": null, "name": "Murphy's Brewery", "point": {"lat": "51.9043448552689)", "lng": "-8.47329852051458"}, "industry": null, "addr:interpolation": null, "addr:housename": null, "microbrewery": null, "craft": null, "osm_id": 129111331, "type": "way"}, "34654117": {"addr:housenumber": null, "amenity": null, "name": "Coors Brewery", "point": {"lat": "53.8853508628974)", "lng": "-1.27153560655616"}, "industry": null, "addr:interpolation": null, "addr:housename": null, "microbrewery": null, "craft": null, "osm_id": 34654117, "type": "way"}, "27236518": {"addr:housenumber": null, "amenity": null, "name": "Guinness Brewery", "point": {"lat": "53.3452302898518)", "lng": "-6.28794109284959"}, "industry": null, "addr:interpolation": null, "addr:housename": null, "microbrewery": null, "craft": null, "osm_id": 27236518, "type": "way"}, "343120423": {"addr:housenumber": null, "amenity": null, "name": "Nottingham Brewery", "point": {"lat": "52.9581887947457)", "lng": "-1.18066619983565"}, "industry": null, "addr:interpolation": null, "addr:housename": null, "microbrewery": null, "craft": null, "osm_id": 343120423, "type": "node"}, "27217128": {"addr:housenumber": null, "amenity": null, "name": "Guinness Brewery", "point": {"lat": "53.341961554155)", "lng": "-6.28573792042104"}, "industry": null, "addr:interpolation": null, "addr:housename": null, "microbrewery": null, "craft": null, "osm_id": 27217128, "type": "way"}, "4993705": {"addr:housenumber": null, "amenity": null, "name": "The Brewery", "point": {"lat": "51.5753988708447)", "lng": "0.180253176164773"}, "industry": null, "addr:interpolation": null, "addr:housename": null, "microbrewery": null, "craft": null, "osm_id": 4993705, "type": "way"}, "4604883": {"addr:housenumber": null, "amenity": null, "name": "Samlesbury Brewery", "point": {"lat": "53.7620144251826)", "lng": "-2.61691970180079"}, "industry": null, "addr:interpolation": null, "addr:housename": null, "microbrewery": null, "craft": null, "osm_id": 4604883, "type": "way"}, "22887156": {"addr:housenumber": null, "amenity": null, "name": "Brewery Mews Business Centre", "point": {"lat": "51.4702485597473)", "lng": "-0.331100103307538"}, "industry": null, "addr:interpolation": null, "addr:housename": null, "microbrewery": null, "craft": null, "osm_id": 22887156, "type": "way"}, "342579647": {"addr:housenumber": null, "amenity": null, "name": "The Old Brewery", "point": {"lat": "53.7949135947326)", "lng": "-1.53793949978592"}, "industry": null, "addr:interpolation": null, "addr:housename": null, "microbrewery": null, "craft": null, "osm_id": 342579647, "type": "node"}, "29146102": {"addr:housenumber": null, "amenity": null, "name": "Coors Brewery", "point": {"lat": "52.8040076322466)", "lng": "-1.63704241947586"}, "industry": null, "addr:interpolation": null, "addr:housename": null, "microbrewery": null, "craft": null, "osm_id": 29146102, "type": "way"}, "34654199": {"addr:housenumber": null, "amenity": null, "name": "John Smith's Brewery", "point": {"lat": "53.8812061430144)", "lng": "-1.2621876636561"}, "industry": null, "addr:interpolation": null, "addr:housename": null, "microbrewery": null, "craft": null, "osm_id": 34654199, "type": "way"}, "31352831": {"addr:housenumber": null, "amenity": null, "name": "Greene King Brewery", "point": {"lat": "52.2412842255678)", "lng": "0.717927525883354"}, "industry": null, "addr:interpolation": null, "addr:housename": null, "microbrewery": null, "craft": null, "osm_id": 31352831, "type": "way"}, "94247167": {"addr:housenumber": null, "amenity": null, "name": "Brains brewery", "point": {"lat": "51.474075699511)", "lng": "-3.18007660954799"}, "industry": null, "addr:interpolation": null, "addr:housename": null, "microbrewery": null, "craft": null, "osm_id": 94247167, "type": "way"}}